mygeo/__init__.py
mygeo/circle.py
mygeo/rectangle.py
mygeo-0.1.dist-info/METADATA
mygeo-0.1.dist-info/WHEEL
mygeo-0.1.dist-info/top_level.txt
mygeo-0.1.dist-info/RECORD
